multiprocnomain/README.MD
multiprocnomain/__init__.py
multiprocnomain/requirements.txt
multiprocnomain/thirdparty.json
multiprocnomain-0.10.dist-info/LICENSE.rst
multiprocnomain-0.10.dist-info/METADATA
multiprocnomain-0.10.dist-info/WHEEL
multiprocnomain-0.10.dist-info/top_level.txt
multiprocnomain-0.10.dist-info/RECORD
