Metadata-Version: 2.1
Name: multiprocnomain
Version: 0.10
Summary: multiprocessing without __main__ 
Home-page: https://github.com/hansalemaos/multiprocnomain
Author: Johannes Fischer
Author-email: aulasparticularesdealemaosp@gmail.com
License: MIT
Keywords: multiprocessing,cpus
Classifier: Development Status :: 4 - Beta
Classifier: Programming Language :: Python :: 3 :: Only
Classifier: Programming Language :: Python :: 3.10
Classifier: Topic :: Software Development :: Libraries :: Python Modules
Classifier: Topic :: Utilities
License-File: LICENSE.rst
Requires-Dist: dill
